sunpath/SunCalculator.py
sunpath/SunInterpolators.py
sunpath/SunPlotter.py
sunpath/SunSpatial.py
sunpath/SunTemporal.py
sunpath/__init__.py
sunpath/colors.py
sunpath/coordinates.py
sunpath-0.1.7.dist-info/LICENSE
sunpath-0.1.7.dist-info/METADATA
sunpath-0.1.7.dist-info/WHEEL
sunpath-0.1.7.dist-info/top_level.txt
sunpath-0.1.7.dist-info/RECORD
