Metadata-Version: 2.1
Name: sunpath
Version: 0.1.7
Summary: Interpolation and integration over sun path for applications in solar energy
Home-page: https://github.com/vg-cyi/SunPath
Author: vg-cyi
License: UNKNOWN
Project-URL: Bug Tracker, https://github.com/vg-cyi/SunPath/issues
Platform: UNKNOWN
Classifier: Programming Language :: Python :: 3
Classifier: License :: OSI Approved :: GNU General Public License v3 (GPLv3)
Classifier: Operating System :: OS Independent
Requires-Python: >=3.6
License-File: LICENSE
Requires-Dist: mathutils
Requires-Dist: suncalc
Requires-Dist: scipy
Requires-Dist: matplotlib
